setup.py
SMIT/__init__.py
SMIT/manage.py
SMIT/prepareServer.py
SMIT/server.py
SMIT/settings.py
SMIT/test.py
SMIT/wsgiserver.py
SMIT.egg-info/PKG-INFO
SMIT.egg-info/SOURCES.txt
SMIT.egg-info/dependency_links.txt
SMIT.egg-info/top_level.txt
SMIT/SMIT/__init__.py
SMIT/SMIT/celery.py
SMIT/SMIT/router.py
SMIT/SMIT/settings.py
SMIT/SMIT/urls.py
SMIT/SMIT/wsgi.py
SMIT/app/__init__.py
SMIT/app/admin.py
SMIT/app/apps.py
SMIT/app/models.py
SMIT/app/tasks.py
SMIT/app/tests.py
SMIT/app/views.py
SMIT/main/__init__.py
SMIT/main/admin.py
SMIT/main/csv_authentification.py
SMIT/main/forms.py
SMIT/main/ldap_authentification.py
SMIT/main/models.py
SMIT/main/mysql_authentification.py
SMIT/main/system_functions.py
SMIT/main/tests.py
SMIT/main/views.py