Metadata-Version: 1.0
Name: SMIT
Version: 0.2
Summary: A package to help automate creation of testing in Django
Home-page: http://code.google.com/p/SMIT/
Author: ELIAS ARNAUD
Author-email: jgaelia@starxpert.fr
License: UNKNOWN
Platform: UNKNOWN
